setup.py
pg_raxarchive/__init__.py
pg_raxarchive/__main__.py
pg_raxarchive/archiver.py
pg_raxarchive.egg-info/PKG-INFO
pg_raxarchive.egg-info/SOURCES.txt
pg_raxarchive.egg-info/dependency_links.txt
pg_raxarchive.egg-info/entry_points.txt
pg_raxarchive.egg-info/requires.txt
pg_raxarchive.egg-info/top_level.txt