Metadata-Version: 1.0
Name: pg-raxarchive
Version: 1.0
Summary: Command line tool to handle Postgresql WAL archiving on Rackspace's cloudfiles.
Home-page: https://github.com/duilio/pg_raxarchive
Author: Maurizio Sambati
Author-email: maurizio@skicelab.com
License: BSD
Platform: UNKNOWN
Classifier: Development Status :: 5 - Production/Stable
Classifier: Intended Audience :: Information Technology
Classifier: Intended Audience :: System Administrators
Classifier: Intended Audience :: Developers
Classifier: Operating System :: POSIX
Classifier: License :: OSI Approved :: BSD License
Classifier: Programming Language :: Python :: 2.7
Classifier: Topic :: Utilities
Classifier: Topic :: Software Development :: Libraries :: Python Modules
